README.md
setup.cfg
setup.py
gcpinfra/__init__.py
gcpinfra.egg-info/PKG-INFO
gcpinfra.egg-info/SOURCES.txt
gcpinfra.egg-info/dependency_links.txt
gcpinfra.egg-info/requires.txt
gcpinfra.egg-info/top_level.txt
gcpinfra/gcd/__init__.py
gcpinfra/gcd/jobs.py
gcpinfra/gcd/workflow.py
gcpinfra/gce/__init__.py
gcpinfra/gce/clusters.py
gcpinfra/gce/conf.py
gcpinfra/gce/machine_deployer.py
gcpinfra/gcp/__init__.py
gcpinfra/gcp/conf.py
gcpinfra/gcp/core.py
gcpinfra/gcs/__init__.py
gcpinfra/gcs/comms.py
gcpinfra/gcs/deployer.py