Metadata-Version: 2.1
Name: gcpinfra
Version: 0.6.3
Summary: Google Cloud Platform non-official framework
Home-page: https://github.com/anewmanvs/gcpinfra
Author: Alex Newman
Author-email: a.newmanvs@gmail.com
License: UNKNOWN
Download-URL: https://github.com/anewmanvs/gcpinfra/archive/v0.6.3.tar.gz
Keywords: gcp,google cloud platform,framework
Platform: UNKNOWN
Classifier: Development Status :: 3 - Alpha
Classifier: Intended Audience :: Developers
Classifier: Operating System :: POSIX :: Linux
Classifier: Programming Language :: Python :: 3
Requires-Python: >=3
